geos18_nexrad_package/__init__.py
geos18_nexrad_package/cli.py
geos18_nexrad_package-0.5.dist-info/METADATA
geos18_nexrad_package-0.5.dist-info/WHEEL
geos18_nexrad_package-0.5.dist-info/entry_points.txt
geos18_nexrad_package-0.5.dist-info/top_level.txt
geos18_nexrad_package-0.5.dist-info/RECORD
