Metadata-Version: 2.1
Name: geos18-nexrad-package
Version: 0.5
Classifier: Programming Language :: Python :: 3
Classifier: License :: OSI Approved :: MIT License
Classifier: Operating System :: OS Independent
Requires-Dist: numpy
Requires-Dist: pandas
Requires-Dist: typer
Requires-Dist: boto3
Requires-Dist: datetime
Requires-Dist: python-dotenv
Requires-Dist: typing ; python_version < "3.9"
